TD2/LongOrfs.py
TD2/Predict.py
TD2/__init__.py
TD2/get_tables.py
TD2/help.py
TD2/translator.py
TD2/tables/__init__.py
TD2/tables/table_1.json
TD2/tables/table_10.json
TD2/tables/table_11.json
TD2/tables/table_12.json
TD2/tables/table_13.json
TD2/tables/table_14.json
TD2/tables/table_15.json
TD2/tables/table_16.json
TD2/tables/table_2.json
TD2/tables/table_21.json
TD2/tables/table_22.json
TD2/tables/table_23.json
TD2/tables/table_24.json
TD2/tables/table_25.json
TD2/tables/table_26.json
TD2/tables/table_27.json
TD2/tables/table_28.json
TD2/tables/table_29.json
TD2/tables/table_3.json
TD2/tables/table_30.json
TD2/tables/table_31.json
TD2/tables/table_33.json
TD2/tables/table_4.json
TD2/tables/table_5.json
TD2/tables/table_6.json
TD2/tables/table_9.json
api/__init__.py
td2-1.0.8.dist-info/licenses/LICENSE.txt
tests/__init__.py
tests/ambiguous_codon_test.py
tests/compare_peps.py
tests/longorfs_low_memory.py
tests/partition_mane.py
tests/test_find_orfs.py
tests/test_find_orfs_real.py
tests/test_reverse_complement.py
tests/test_translate.py
tests/visualize_benchmark.py
tests/visualize_chess.py
tests/visualize_mane_composition.py
tests/data/__init__.py
td2-1.0.8.dist-info/METADATA
td2-1.0.8.dist-info/WHEEL
td2-1.0.8.dist-info/entry_points.txt
td2-1.0.8.dist-info/top_level.txt
td2-1.0.8.dist-info/RECORD
